rchp/__init__.py
rchp/crchp.cpython-310-x86_64-linux-gnu.so
rchp-0.2.1.dist-info/METADATA
rchp-0.2.1.dist-info/WHEEL
rchp-0.2.1.dist-info/RECORD
rchp-0.2.1.dist-info/licenses/LICENSE
