Metadata-Version: 2.1
Name: rchp
Version: 0.2.1
Author-Email: enstarep <enstarep@rncyk.org>
License: MIT
Requires-Python: >=3.10
